gccoutputparser/__init__.py
gccoutputparser/gccoutputparser.py
gccoutputparser-0.1.dist-info/METADATA
gccoutputparser-0.1.dist-info/WHEEL
gccoutputparser-0.1.dist-info/top_level.txt
gccoutputparser-0.1.dist-info/RECORD
